{
  "generator-jhipster": {
    "appsFolders": [
      "invoice",
      "notification",
      "store"
    ],
    "directoryPath": "../",
    "clusteredDbApps": [
      "notification"
    ],
    "serviceDiscoveryType": "eureka",
    "jwtSecretKey": "Mjc3NjA4M2NmMzBhNTZmODUzMzdlODI5NzFiZTVhYWI4ZjZmMjlhZDJlODY1NDY1OGE4NWUzNTNmN2RiZWRhMDk5MDg3MTA3ZmRmZTEzODZhNTAxN2YxN2VlNDc0ZjQ0YjgwZQ==",
    "dockerRepositoryName": "efrengarcial",
    "dockerPushCommand": "docker push",
    "kubernetesNamespace": "jhipster",
    "kubernetesServiceType": "NodePort",
    "monitoring": "elk",
    "istio": "no",
    "istioRoute": false
  }
}